[
    {
        "host_name": "khaled",
        "Event": "Spiel gestartet",
        "max_spieler": 2,
        "timestamp": "19-06-2024 00:50:38 Uhr"
    },
    {
        "host_name": "khaled",
        "button_text": "Packet",
        "x_wert": 0,
        "y_wert": 2,
        "auswahl_zeitpunkt": "19-06-2024 00:50:47 Uhr"
    },
    {
        "host_name": "khaled",
        "button_text": "Cookie",
        "x_wert": 1,
        "y_wert": 3,
        "auswahl_zeitpunkt": "19-06-2024 00:50:55 Uhr"
    },
    {
        "host_name": "khaled",
        "button_text": "Versionierung",
        "x_wert": 2,
        "y_wert": 3,
        "auswahl_zeitpunkt": "19-06-2024 00:50:55 Uhr"
    },
    {
        "host_name": "khaled",
        "Event": "GEWONNEN",
        "timestamp": "19-06-2024 00:50:55 Uhr"
    },
    {
        "host_name": "khaled",
        "Event": "Spiel gestartet",
        "max_spieler": 2,
        "timestamp": "19-06-2024 01:09:22 Uhr"
    },
    {
        "host_name": "khaled",
        "button_text": "NoSQL",
        "x_wert": 0,
        "y_wert": 4,
        "auswahl_zeitpunkt": "19-06-2024 01:09:26 Uhr"
    },
    {
        "host_name": "khaled",
        "Event": "Spiel gestartet",
        "max_spieler": 2,
        "timestamp": "19-06-2024 01:11:20 Uhr"
    },
    {
        "host_name": "khaled",
        "button_text": "Hosting",
        "x_wert": 0,
        "y_wert": 3,
        "auswahl_zeitpunkt": "19-06-2024 01:11:22 Uhr"
    },
    {
        "host_name": "khaled",
        "button_text": "IoT",
        "x_wert": 1,
        "y_wert": 3,
        "auswahl_zeitpunkt": "19-06-2024 01:11:23 Uhr"
    },
    {
        "host_name": "khaled",
        "button_text": "Kernel",
        "x_wert": 2,
        "y_wert": 3,
        "auswahl_zeitpunkt": "19-06-2024 01:11:23 Uhr"
    },
    {
        "host_name": "khaled",
        "button_text": "JOKER",
        "x_wert": 3,
        "y_wert": 3,
        "auswahl_zeitpunkt": "19-06-2024 01:11:24 Uhr"
    },
    {
        "host_name": "khaled",
        "button_text": "App",
        "x_wert": 4,
        "y_wert": 3,
        "auswahl_zeitpunkt": "19-06-2024 01:11:29 Uhr"
    },
    {
        "host_name": "khaled",
        "button_text": "VPN",
        "x_wert": 5,
        "y_wert": 3,
        "auswahl_zeitpunkt": "19-06-2024 01:11:30 Uhr"
    },
    {
        "host_name": "khaled",
        "button_text": "Firewall",
        "x_wert": 0,
        "y_wert": 4,
        "auswahl_zeitpunkt": "19-06-2024 01:11:32 Uhr"
    },
    {
        "host_name": "khaled",
        "button_text": "Hacker",
        "x_wert": 0,
        "y_wert": 5,
        "auswahl_zeitpunkt": "19-06-2024 01:11:33 Uhr"
    },
    {
        "host_name": "khaled",
        "button_text": "Blockchain",
        "x_wert": 0,
        "y_wert": 2,
        "auswahl_zeitpunkt": "19-06-2024 01:11:34 Uhr"
    },
    {
        "host_name": "khaled",
        "button_text": "Pixel",
        "x_wert": 0,
        "y_wert": 1,
        "auswahl_zeitpunkt": "19-06-2024 01:11:34 Uhr"
    },
    {
        "host_name": "khaled",
        "button_text": "Scrum",
        "x_wert": 0,
        "y_wert": 0,
        "auswahl_zeitpunkt": "19-06-2024 01:11:35 Uhr"
    },
    {
        "host_name": "khaled",
        "button_text": "Server",
        "x_wert": 1,
        "y_wert": 2,
        "auswahl_zeitpunkt": "19-06-2024 01:33:40 Uhr"
    },
    {
        "host_name": "khaled",
        "Event": "Spiel gestartet",
        "max_spieler": null,
        "timestamp": "19-06-2024 15:24:12 Uhr"
    },
    {
        "host_name": "khaled",
        "Event": "Spiel gestartet",
        "max_spieler": 2,
        "timestamp": "19-06-2024 15:25:44 Uhr"
    },
    {
        "host_name": "khaled",
        "Event": "Spiel gestartet",
        "max_spieler": 2,
        "timestamp": "19-06-2024 15:26:00 Uhr"
    },
    {
        "host_name": "khaled",
        "Event": "Spiel gestartet",
        "max_spieler": 2,
        "timestamp": "19-06-2024 15:28:07 Uhr"
    },
    {
        "host_name": "khaled",
        "button_text": "Shell",
        "x_wert": 0,
        "y_wert": 0,
        "auswahl_zeitpunkt": "19-06-2024 15:28:08 Uhr"
    }
]